cardlink/__init__.py
cardlink/__meta__.py
cardlink/client.py
cardlink/client.pyi
cardlink/error.py
cardlink/loggers.py
cardlink/api/__init__.py
cardlink/api/aiohttp.py
cardlink/api/base.py
cardlink/methods/__init__.py
cardlink/methods/base.py
cardlink/methods/billPayments.py
cardlink/methods/billStatus.py
cardlink/methods/createBill.py
cardlink/methods/createFullRefund.py
cardlink/methods/createPartialRefund.py
cardlink/methods/createPersonalPayout.py
cardlink/methods/createRegularPayout.py
cardlink/methods/getBalance.py
cardlink/methods/getBanks.py
cardlink/methods/paymentStatus.py
cardlink/methods/payoutStatus.py
cardlink/methods/refundStatus.py
cardlink/methods/searchBill.py
cardlink/methods/searchPayments.py
cardlink/methods/searchPayout.py
cardlink/methods/searchRefund.py
cardlink/methods/toggleActivity.py
cardlink/types/Balance.py
cardlink/types/Balances.py
cardlink/types/Bank.py
cardlink/types/Banks.py
cardlink/types/Bill.py
cardlink/types/BillStatus.py
cardlink/types/BillTypes.py
cardlink/types/CreatedBill.py
cardlink/types/Crypto.py
cardlink/types/Currency.py
cardlink/types/Item.py
cardlink/types/Links.py
cardlink/types/Meta.py
cardlink/types/Payment.py
cardlink/types/PaymentMethod.py
cardlink/types/PaymentStatus.py
cardlink/types/Payout.py
cardlink/types/PayoutStatus.py
cardlink/types/Payouts.py
cardlink/types/Refund.py
cardlink/types/RefundStatus.py
cardlink/types/RefundType.py
cardlink/types/SearchedBill.py
cardlink/types/SearchedPayments.py
cardlink/types/SearchedPayout.py
cardlink/types/SearchedRefund.py
cardlink/types/__init__.py
cardlink/types/base.py
cardlink/utils/check_token.py
cardlink/utils/clean_dict.py
cardlink-1.0.4.dist-info/licenses/LICENSE
cardlink-1.0.4.dist-info/METADATA
cardlink-1.0.4.dist-info/WHEEL
cardlink-1.0.4.dist-info/top_level.txt
cardlink-1.0.4.dist-info/RECORD
